noot/__init__.py
noot/addons/spy_mode.py
noot/assertions.py
noot/cache.py
noot/cli.py
noot/flow.py
noot/init.py
noot/llm.py
noot/mitmproxy_manager.py
noot/parser.py
noot/project.py
noot/step.py
noot/templates/cli.py.template
noot/templates/pyproject.toml.template
noot/templates/test_cli.py.template
noot/terminal.py
noot-0.1.0.dist-info/WHEEL
noot-0.1.0.dist-info/entry_points.txt
noot-0.1.0.dist-info/METADATA
noot-0.1.0.dist-info/RECORD
