Metadata-Version: 2.3
Name: noot
Version: 0.1.0
Summary: noot library
Author: Jack Jackson, Armin Stepanyan
Requires-Dist: anthropic>=0.76.0
Requires-Dist: mitmproxy
Requires-Dist: rich
Requires-Python: >=3.12
